bbperf/.gitignore
bbperf/__init__.py
bbperf/bbperf.py
bbperf/client.py
bbperf/const.py
bbperf/control_receiver_thread.py
bbperf/data_receiver_thread.py
bbperf/data_sample_evaluator_class.py
bbperf/data_sender_thread.py
bbperf/exceptions.py
bbperf/graph.py
bbperf/json_output_class.py
bbperf/output.py
bbperf/run_mode_manager_class.py
bbperf/server.py
bbperf/tcp-graph.gp
bbperf/tcp_control_connection_class.py
bbperf/tcp_helper.py
bbperf/udp-graph.gp
bbperf/udp_helper.py
bbperf/udp_rate_manager_class.py
bbperf/udp_string_sender_thread.py
bbperf/util.py
bbperf-0.0.32.dist-info/METADATA
bbperf-0.0.32.dist-info/WHEEL
bbperf-0.0.32.dist-info/entry_points.txt
bbperf-0.0.32.dist-info/licenses/LICENSE
bbperf-0.0.32.dist-info/RECORD
