Metadata-Version: 2.4
Name: bbperf
Version: 0.0.32
Summary: An end-to-end performance and bufferbloat measurement tool
Project-URL: Homepage, https://github.com/cloudflare/bbperf
Project-URL: Issues, https://github.com/cloudflare/bbperf/issues
Author-email: Mike Freemon <mfreemon@cloudflare.com>
License-Expression: Apache-2.0
License-File: LICENSE
Classifier: Environment :: Console
Classifier: License :: OSI Approved :: Apache Software License
Classifier: Operating System :: OS Independent
Classifier: Programming Language :: Python :: 3
Classifier: Topic :: System :: Networking
Requires-Python: >=3.9
Requires-Dist: numpy
